setup.py
vaccine/__init__.py
vaccine/_version.py
vaccine/exceptions.py
vaccine/vaccine.py
vaccine.egg-info/PKG-INFO
vaccine.egg-info/SOURCES.txt
vaccine.egg-info/dependency_links.txt
vaccine.egg-info/top_level.txt
vaccine/tests/__init__.py
vaccine/tests/test_vaccine.py