Metadata-Version: 1.1
Name: vaccine
Version: 0.1.0
Summary: A simple dependency injection framework
Home-page: http://github.com/duckworthd/vaccine
Author: Daniel Duckworth
Author-email: duckworthd@gmail.com
License: BSD
Keywords: di dependency injection
Platform: UNKNOWN
Classifier: Development Status :: 4 - Beta
Classifier: Programming Language :: Python
